schul_cloud_resources_api_v1/__init__.py
schul_cloud_resources_api_v1/api_client.py
schul_cloud_resources_api_v1/auth.py
schul_cloud_resources_api_v1/configuration.py
schul_cloud_resources_api_v1/rest.py
schul_cloud_resources_api_v1/apis/__init__.py
schul_cloud_resources_api_v1/apis/resource_api.py
schul_cloud_resources_api_v1/models/__init__.py
schul_cloud_resources_api_v1/models/error_element.py
schul_cloud_resources_api_v1/models/error_response.py
schul_cloud_resources_api_v1/models/jsonapi.py
schul_cloud_resources_api_v1/models/resource.py
schul_cloud_resources_api_v1/models/resource_ids_response.py
schul_cloud_resources_api_v1/models/resource_ids_response_data.py
schul_cloud_resources_api_v1/models/resource_ids_response_links.py
schul_cloud_resources_api_v1/models/resource_post.py
schul_cloud_resources_api_v1/models/resource_post_data.py
schul_cloud_resources_api_v1/models/resource_response.py
schul_cloud_resources_api_v1/models/resource_response_data.py
schul_cloud_resources_api_v1/models/resource_response_links.py
schul_cloud_resources_api_v1/models/resource_type.py
schul_cloud_resources_api_v1/schema/__init__.py
schul_cloud_ressources_api_v1-1.0.0.64.dist-info/DESCRIPTION.rst
schul_cloud_ressources_api_v1-1.0.0.64.dist-info/METADATA
schul_cloud_ressources_api_v1-1.0.0.64.dist-info/RECORD
schul_cloud_ressources_api_v1-1.0.0.64.dist-info/WHEEL
schul_cloud_ressources_api_v1-1.0.0.64.dist-info/metadata.json
schul_cloud_ressources_api_v1-1.0.0.64.dist-info/top_level.txt
test/__init__.py
test/test_authentication.py
test/test_error_element.py
test/test_error_response.py
test/test_jsonapi.py
test/test_resource.py
test/test_resource_api.py
test/test_resource_ids_response.py
test/test_resource_ids_response_data.py
test/test_resource_ids_response_links.py
test/test_resource_post.py
test/test_resource_post_data.py
test/test_resource_response.py
test/test_resource_response_data.py
test/test_resource_response_links.py
test/test_resource_type.py
test/test_schema.py
