Metadata-Version: 2.0
Name: schul-cloud-ressources-api-v1
Version: 1.0.0.64
Summary: Schul-Cloud Content API
Home-page: https://github.com/schul-cloud/ressources-api-v1
Author: UNKNOWN
Author-email: UNKNOWN
License: UNKNOWN
Keywords: Swagger,Schul-Cloud Content API
Platform: UNKNOWN
Requires-Dist: certifi (>=14.05.14)
Requires-Dist: jsonschema (==2.6.0)
Requires-Dist: python-dateutil (>=2.5.3)
Requires-Dist: setuptools (>=21.0.0)
Requires-Dist: six (>=1.10)
Requires-Dist: urllib3 (>=1.15.1)
